stoicquote.py
data/__init__.py
data/quotes
stoicquote-0.1.0.dist-info/METADATA
stoicquote-0.1.0.dist-info/WHEEL
stoicquote-0.1.0.dist-info/entry_points.txt
stoicquote-0.1.0.dist-info/top_level.txt
stoicquote-0.1.0.dist-info/RECORD
